{
  "hit": {
    "totalcmd": 266,
    "todaycmd": 8,
    "menu": 18,
    "groupmenu": 2,
    "qc": 3,
    "owner": 1,
    "ownermenu": 1,
    "bot": 6,
    "autoread": 3,
    "readsw": 2,
    "brat": 12,
    "warn": 2,
    "ping": 14,
    "suit": 19,
    "allmenu": 13,
    "profile": 4,
    "leaderboard": 5,
    "transfer": 6,
    "coba": 1,
    "tf": 3,
    "d": 25,
    "kick": 6,
    "delsuit": 4,
    "play": 4,
    "swm": 9,
    "ytmp3": 3,
    "tebakkata": 2,
    "tebakgambar": 5,
    "slot": 2,
    "susunkata": 2,
    "tagall": 9,
    "h": 3,
    "afk": 3,
    "toimg": 2,
    "s": 6,
    "trigger": 2,
    "setwelcome": 8,
    "welcome": 3,
    "demote": 3,
    "promote": 1,
    "siapakah": 2,
    "cekkhodam": 1,
    "linkgc": 3,
    "del": 1,
    "ceknawala": 1,
    "delete": 1,
    "smeme": 1,
    "rvo": 2,
    "anticall": 7,
    "hd": 6,
    "totag": 5,
    "tt": 1,
    "sc": 1,
    "addprem": 2,
    "gamemenu": 1,
    "cek": 1,
    "remini": 1,
    "group": 8,
    "setleave": 1,
    "tes": 1,
    "ig": 1,
    "spotify": 1
  },
  "set": {
    "855889492335@s.whatsapp.net": {
      "lang": "id",
      "limit": 2,
      "uang": 0,
      "status": 0,
      "join": false,
      "public": true,
      "anticall": true,
      "original": true,
      "readsw": false,
      "autobio": false,
      "autoread": true,
      "antispam": false,
      "autotyping": true,
      "grouponly": true,
      "multiprefix": false,
      "privateonly": true,
      "autobackup": false,
      "template": "listMessage"
    }
  },
  "users": {
    "855889492335@s.whatsapp.net": {
      "vip": false,
      "ban": false,
      "afkTime": -1,
      "afkReason": "",
      "limit": 20,
      "uang": 10000,
      "lastclaim": 1744309652185,
      "lastbegal": 1744309652185,
      "lastrampok": 1744309652185
    },
    "6282137829041@s.whatsapp.net": {
      "vip": false,
      "ban": false,
      "afkTime": -1,
      "afkReason": "",
      "limit": 20,
      "uang": 8410,
      "lastclaim": 1744309656155,
      "lastbegal": 1744309656155,
      "lastrampok": 1744309656155
    },
    "6282170170785@s.whatsapp.net": {
      "vip": false,
      "ban": false,
      "afkTime": -1,
      "afkReason": "",
      "limit": 23,
      "uang": 13050,
      "lastclaim": 1744310024923,
      "lastbegal": 1744310024923,
      "lastrampok": 1744310024923
    },
    "62882003382430@s.whatsapp.net": {
      "vip": false,
      "ban": false,
      "afkTime": -1,
      "afkReason": "",
      "limit": 19,
      "uang": 47523,
      "lastclaim": 1744310076756,
      "lastbegal": 1744310076756,
      "lastrampok": 1744310076756
    },
    "120363366790950043@newsletter": {
      "vip": false,
      "ban": false,
      "afkTime": -1,
      "afkReason": "",
      "limit": 20,
      "uang": 10000,
      "lastclaim": 1744315322865,
      "lastbegal": 1744315322865,
      "lastrampok": 1744315322865
    },
    "120363040135174965@g.us": {
      "vip": false,
      "ban": false,
      "afkTime": -1,
      "afkReason": "",
      "limit": 20,
      "uang": 10000,
      "lastclaim": 1744322401527,
      "lastbegal": 1744322401527,
      "lastrampok": 1744322401527
    },
    "6282189395216@s.whatsapp.net": {
      "vip": false,
      "ban": false,
      "afkTime": -1,
      "afkReason": "",
      "limit": 20,
      "uang": 10000,
      "lastclaim": 1744322626983,
      "lastbegal": 1744322626983,
      "lastrampok": 1744322626983
    },
    "6283170061373@s.whatsapp.net": {
      "vip": false,
      "ban": false,
      "afkTime": -1,
      "afkReason": "",
      "limit": 20,
      "uang": 10000,
      "lastclaim": 1744333235274,
      "lastbegal": 1744333235274,
      "lastrampok": 1744333235274
    },
    "6285647026769@s.whatsapp.net": {
      "vip": false,
      "ban": false,
      "afkTime": -1,
      "afkReason": "",
      "limit": 20,
      "uang": 10000,
      "lastclaim": 1744333299136,
      "lastbegal": 1744333299136,
      "lastrampok": 1744333299136
    },
    "6285882439491@s.whatsapp.net": {
      "vip": false,
      "ban": false,
      "afkTime": -1,
      "afkReason": "",
      "limit": 20,
      "uang": 10000,
      "lastclaim": 1744334116736,
      "lastbegal": 1744334116736,
      "lastrampok": 1744334116736
    },
    "6285154030539@s.whatsapp.net": {
      "vip": false,
      "ban": false,
      "afkTime": -1,
      "afkReason": "",
      "limit": 20,
      "uang": 10000,
      "lastclaim": 1744336347079,
      "lastbegal": 1744336347079,
      "lastrampok": 1744336347079
    },
    "6281360129480@s.whatsapp.net": {
      "vip": false,
      "ban": false,
      "afkTime": -1,
      "afkReason": "",
      "limit": 20,
      "uang": 10000,
      "lastclaim": 1744336444805,
      "lastbegal": 1744336444805,
      "lastrampok": 1744336444805
    },
    "628882436209@s.whatsapp.net": {
      "vip": false,
      "ban": false,
      "afkTime": -1,
      "afkReason": "",
      "limit": 20,
      "uang": 10000,
      "lastclaim": 1744337886480,
      "lastbegal": 1744337886480,
      "lastrampok": 1744337886480
    },
    "6289684409213@s.whatsapp.net": {
      "vip": false,
      "ban": false,
      "afkTime": -1,
      "afkReason": "",
      "limit": 20,
      "uang": 10000,
      "lastclaim": 1744338649367,
      "lastbegal": 1744338649367,
      "lastrampok": 1744338649367
    },
    "62895321008608@s.whatsapp.net": {
      "vip": false,
      "ban": false,
      "afkTime": -1,
      "afkReason": "",
      "limit": 20,
      "uang": 10000,
      "lastclaim": 1744340145231,
      "lastbegal": 1744340145231,
      "lastrampok": 1744340145231
    },
    "6282241642302@s.whatsapp.net": {
      "vip": false,
      "ban": false,
      "afkTime": -1,
      "afkReason": "",
      "limit": 20,
      "uang": 10000,
      "lastclaim": 1744343975164,
      "lastbegal": 1744343975164,
      "lastrampok": 1744343975164
    },
    "6281373270594@s.whatsapp.net": {
      "vip": false,
      "ban": false,
      "afkTime": -1,
      "afkReason": "",
      "limit": 20,
      "uang": 10000,
      "lastclaim": 1744344146663,
      "lastbegal": 1744344146663,
      "lastrampok": 1744344146663
    },
    "6289664547774@s.whatsapp.net": {
      "vip": false,
      "ban": false,
      "afkTime": -1,
      "afkReason": "",
      "limit": 20,
      "uang": 10000,
      "lastclaim": 1744345609021,
      "lastbegal": 1744345609021,
      "lastrampok": 1744345609021
    },
    "628977923697@s.whatsapp.net": {
      "vip": false,
      "ban": false,
      "afkTime": 1744437820373,
      "afkReason": "",
      "limit": 20,
      "uang": 10000,
      "lastclaim": 1744346575621,
      "lastbegal": 1744346575621,
      "lastrampok": 1744346575621
    },
    "6285198016574@s.whatsapp.net": {
      "vip": false,
      "ban": false,
      "afkTime": -1,
      "afkReason": "",
      "limit": 20,
      "uang": 10000,
      "lastclaim": 1744352824512,
      "lastbegal": 1744352824512,
      "lastrampok": 1744352824512
    },
    "60187829080@s.whatsapp.net": {
      "vip": false,
      "ban": false,
      "afkTime": -1,
      "afkReason": "",
      "limit": 20,
      "uang": 10000,
      "lastclaim": 1744352836837,
      "lastbegal": 1744352836837,
      "lastrampok": 1744352836837
    },
    "62895334617098@s.whatsapp.net": {
      "vip": false,
      "ban": false,
      "afkTime": -1,
      "afkReason": "",
      "limit": 20,
      "uang": 10000,
      "lastclaim": 1744352859311,
      "lastbegal": 1744352859311,
      "lastrampok": 1744352859311
    },
    "6289649892172@s.whatsapp.net": {
      "vip": false,
      "ban": false,
      "afkTime": -1,
      "afkReason": "",
      "limit": 20,
      "uang": 10000,
      "lastclaim": 1744353030941,
      "lastbegal": 1744353030941,
      "lastrampok": 1744353030941
    },
    "62882019863586@s.whatsapp.net": {
      "vip": false,
      "ban": false,
      "afkTime": -1,
      "afkReason": "",
      "limit": 20,
      "uang": 10000,
      "lastclaim": 1744354307895,
      "lastbegal": 1744354307895,
      "lastrampok": 1744354307895
    },
    "6283807642828@s.whatsapp.net": {
      "vip": false,
      "ban": false,
      "afkTime": -1,
      "afkReason": "",
      "limit": 20,
      "uang": 10000,
      "lastclaim": 1744354397161,
      "lastbegal": 1744354397161,
      "lastrampok": 1744354397161
    },
    "31687173992@s.whatsapp.net": {
      "vip": false,
      "ban": false,
      "afkTime": -1,
      "afkReason": "",
      "limit": 20,
      "uang": 10000,
      "lastclaim": 1744354413142,
      "lastbegal": 1744354413142,
      "lastrampok": 1744354413142
    },
    "6285187472989@s.whatsapp.net": {
      "vip": false,
      "ban": false,
      "afkTime": -1,
      "afkReason": "",
      "limit": 20,
      "uang": 10000,
      "lastclaim": 1744354440587,
      "lastbegal": 1744354440587,
      "lastrampok": 1744354440587
    },
    "6283892969926@s.whatsapp.net": {
      "vip": false,
      "ban": false,
      "afkTime": -1,
      "afkReason": "",
      "limit": 20,
      "uang": 10000,
      "lastclaim": 1744355210926,
      "lastbegal": 1744355210926,
      "lastrampok": 1744355210926
    },
    "6285793466439@s.whatsapp.net": {
      "vip": false,
      "ban": false,
      "afkTime": -1,
      "afkReason": "",
      "limit": 1018,
      "uang": 1010000,
      "lastclaim": 1744355337045,
      "lastbegal": 1744355337045,
      "lastrampok": 1744355337045
    },
    "6285795945652@s.whatsapp.net": {
      "vip": false,
      "ban": false,
      "afkTime": -1,
      "afkReason": "",
      "limit": 20,
      "uang": 10000,
      "lastclaim": 1744355741706,
      "lastbegal": 1744355741706,
      "lastrampok": 1744355741706
    },
    "6285134561819@s.whatsapp.net": {
      "vip": false,
      "ban": false,
      "afkTime": -1,
      "afkReason": "",
      "limit": 20,
      "uang": 10000,
      "lastclaim": 1744356122530,
      "lastbegal": 1744356122530,
      "lastrampok": 1744356122530
    },
    "6285134561147@s.whatsapp.net": {
      "vip": false,
      "ban": false,
      "afkTime": -1,
      "afkReason": "",
      "limit": 20,
      "uang": 10000,
      "lastclaim": 1744356759571,
      "lastbegal": 1744356759571,
      "lastrampok": 1744356759571
    },
    "6285136548910@s.whatsapp.net": {
      "vip": false,
      "ban": false,
      "afkTime": -1,
      "afkReason": "",
      "limit": 20,
      "uang": 10000,
      "lastclaim": 1744357393716,
      "lastbegal": 1744357393716,
      "lastrampok": 1744357393716
    },
    "6285960165491@s.whatsapp.net": {
      "vip": false,
      "ban": false,
      "afkTime": -1,
      "afkReason": "",
      "limit": 20,
      "uang": 10000,
      "lastclaim": 1744363826104,
      "lastbegal": 1744363826104,
      "lastrampok": 1744363826104
    },
    "628811690632@s.whatsapp.net": {
      "vip": false,
      "ban": false,
      "afkTime": -1,
      "afkReason": "",
      "limit": 20,
      "uang": 10000,
      "lastclaim": 1744373337821,
      "lastbegal": 1744373337821,
      "lastrampok": 1744373337821
    },
    "6285934760269@s.whatsapp.net": {
      "vip": false,
      "ban": false,
      "afkTime": -1,
      "afkReason": "",
      "limit": 20,
      "uang": 10000,
      "lastclaim": 1744379183911,
      "lastbegal": 1744379183911,
      "lastrampok": 1744379183911
    },
    "6285182475170@s.whatsapp.net": {
      "vip": false,
      "ban": false,
      "afkTime": -1,
      "afkReason": "",
      "limit": 20,
      "uang": 10000,
      "lastclaim": 1744382802230,
      "lastbegal": 1744382802230,
      "lastrampok": 1744382802230
    },
    "6288287755837@s.whatsapp.net": {
      "vip": false,
      "ban": false,
      "afkTime": -1,
      "afkReason": "",
      "limit": 20,
      "uang": 10000,
      "lastclaim": 1744391208054,
      "lastbegal": 1744391208054,
      "lastrampok": 1744391208054
    },
    "60173067436@s.whatsapp.net": {
      "vip": false,
      "ban": false,
      "afkTime": -1,
      "afkReason": "",
      "limit": 20,
      "uang": 10000,
      "lastclaim": 1744391231044,
      "lastbegal": 1744391231044,
      "lastrampok": 1744391231044
    },
    "6282316387182@s.whatsapp.net": {
      "vip": false,
      "ban": false,
      "afkTime": -1,
      "afkReason": "",
      "limit": 20,
      "uang": 10000,
      "lastclaim": 1744391254254,
      "lastbegal": 1744391254254,
      "lastrampok": 1744391254254
    },
    "6285819515596@s.whatsapp.net": {
      "vip": false,
      "ban": false,
      "afkTime": -1,
      "afkReason": "",
      "limit": 20,
      "uang": 10000,
      "lastclaim": 1744391301906,
      "lastbegal": 1744391301906,
      "lastrampok": 1744391301906
    },
    "6285182384100@s.whatsapp.net": {
      "vip": false,
      "ban": false,
      "afkTime": -1,
      "afkReason": "",
      "limit": 20,
      "uang": 10000,
      "lastclaim": 1744391453699,
      "lastbegal": 1744391453699,
      "lastrampok": 1744391453699
    },
    "6287860585409@s.whatsapp.net": {
      "vip": false,
      "ban": false,
      "afkTime": -1,
      "afkReason": "",
      "limit": 20,
      "uang": 10000,
      "lastclaim": 1744391628443,
      "lastbegal": 1744391628443,
      "lastrampok": 1744391628443
    },
    "6283898063257@s.whatsapp.net": {
      "vip": false,
      "ban": false,
      "afkTime": -1,
      "afkReason": "",
      "limit": 20,
      "uang": 10000,
      "lastclaim": 1744391877262,
      "lastbegal": 1744391877262,
      "lastrampok": 1744391877262
    },
    "6285771674230@s.whatsapp.net": {
      "vip": false,
      "ban": false,
      "afkTime": -1,
      "afkReason": "",
      "limit": 20,
      "uang": 10000,
      "lastclaim": 1744392965956,
      "lastbegal": 1744392965956,
      "lastrampok": 1744392965956
    },
    "6288215910706@s.whatsapp.net": {
      "vip": false,
      "ban": false,
      "afkTime": -1,
      "afkReason": "",
      "limit": 20,
      "uang": 10000,
      "lastclaim": 1744400572940,
      "lastbegal": 1744400572940,
      "lastrampok": 1744400572940
    },
    "6289699287452@s.whatsapp.net": {
      "vip": false,
      "ban": false,
      "afkTime": -1,
      "afkReason": "",
      "limit": 20,
      "uang": 10000,
      "lastclaim": 1744400985454,
      "lastbegal": 1744400985454,
      "lastrampok": 1744400985454
    },
    "62895422499020@s.whatsapp.net": {
      "vip": false,
      "ban": false,
      "afkTime": -1,
      "afkReason": "",
      "limit": 20,
      "uang": 10000,
      "lastclaim": 1744410995396,
      "lastbegal": 1744410995396,
      "lastrampok": 1744410995396
    },
    "6289604039998@s.whatsapp.net": {
      "vip": false,
      "ban": false,
      "afkTime": -1,
      "afkReason": "",
      "limit": 20,
      "uang": 10000,
      "lastclaim": 1744413128376,
      "lastbegal": 1744413128376,
      "lastrampok": 1744413128376
    },
    "6289675617893@s.whatsapp.net": {
      "vip": false,
      "ban": false,
      "afkTime": -1,
      "afkReason": "",
      "limit": 20,
      "uang": 10000,
      "lastclaim": 1744418609303,
      "lastbegal": 1744418609303,
      "lastrampok": 1744418609303
    },
    "6283165112025@s.whatsapp.net": {
      "vip": false,
      "ban": false,
      "afkTime": -1,
      "afkReason": "",
      "limit": 20,
      "uang": 10000,
      "lastclaim": 1744427409665,
      "lastbegal": 1744427409665,
      "lastrampok": 1744427409665
    },
    "6283866837241@s.whatsapp.net": {
      "vip": false,
      "ban": false,
      "afkTime": -1,
      "afkReason": "",
      "limit": 20,
      "uang": 10000,
      "lastclaim": 1744430018157,
      "lastbegal": 1744430018157,
      "lastrampok": 1744430018157
    },
    "6282252503425@s.whatsapp.net": {
      "vip": false,
      "ban": false,
      "afkTime": -1,
      "afkReason": "",
      "limit": 20,
      "uang": 10000,
      "lastclaim": 1744434475277,
      "lastbegal": 1744434475277,
      "lastrampok": 1744434475277
    },
    "6287776340637@s.whatsapp.net": {
      "vip": false,
      "ban": false,
      "afkTime": -1,
      "afkReason": "",
      "limit": 20,
      "uang": 10000,
      "lastclaim": 1744434663794,
      "lastbegal": 1744434663794,
      "lastrampok": 1744434663794
    },
    "6281907195440@s.whatsapp.net": {
      "vip": false,
      "ban": false,
      "afkTime": -1,
      "afkReason": "",
      "limit": 20,
      "uang": 10000,
      "lastclaim": 1744434883522,
      "lastbegal": 1744434883522,
      "lastrampok": 1744434883522
    },
    "6282248431459@s.whatsapp.net": {
      "vip": false,
      "ban": false,
      "afkTime": -1,
      "afkReason": "",
      "limit": 20,
      "uang": 10000,
      "lastclaim": 1744434962914,
      "lastbegal": 1744434962914,
      "lastrampok": 1744434962914
    },
    "6283124279331@s.whatsapp.net": {
      "vip": false,
      "ban": false,
      "afkTime": -1,
      "afkReason": "",
      "limit": 20,
      "uang": 10000,
      "lastclaim": 1744435287849,
      "lastbegal": 1744435287849,
      "lastrampok": 1744435287849
    },
    "6282199225770@s.whatsapp.net": {
      "vip": false,
      "ban": false,
      "afkTime": -1,
      "afkReason": "",
      "limit": 20,
      "uang": 10000,
      "lastclaim": 1744435296271,
      "lastbegal": 1744435296271,
      "lastrampok": 1744435296271
    },
    "6285757797976@s.whatsapp.net": {
      "vip": false,
      "ban": false,
      "afkTime": -1,
      "afkReason": "",
      "limit": 20,
      "uang": 10000,
      "lastclaim": 1744435417397,
      "lastbegal": 1744435417397,
      "lastrampok": 1744435417397
    },
    "6285339257912@s.whatsapp.net": {
      "vip": false,
      "ban": false,
      "afkTime": -1,
      "afkReason": "",
      "limit": 20,
      "uang": 10000,
      "lastclaim": 1744436334446,
      "lastbegal": 1744436334446,
      "lastrampok": 1744436334446
    },
    "6283857231702@s.whatsapp.net": {
      "vip": false,
      "ban": false,
      "afkTime": -1,
      "afkReason": "",
      "limit": 20,
      "uang": 10000,
      "lastclaim": 1744437828300,
      "lastbegal": 1744437828300,
      "lastrampok": 1744437828300
    },
    "6287881296489@s.whatsapp.net": {
      "vip": false,
      "ban": false,
      "afkTime": -1,
      "afkReason": "",
      "limit": 20,
      "uang": 10000,
      "lastclaim": 1744437902073,
      "lastbegal": 1744437902073,
      "lastrampok": 1744437902073
    },
    "6282173059957@s.whatsapp.net": {
      "vip": false,
      "ban": false,
      "afkTime": -1,
      "afkReason": "",
      "limit": 20,
      "uang": 10000,
      "lastclaim": 1744437927756,
      "lastbegal": 1744437927756,
      "lastrampok": 1744437927756
    },
    "6282143772802@s.whatsapp.net": {
      "vip": false,
      "ban": false,
      "afkTime": -1,
      "afkReason": "",
      "limit": 20,
      "uang": 10000,
      "lastclaim": 1744438644639,
      "lastbegal": 1744438644639,
      "lastrampok": 1744438644639
    },
    "6285788482385@s.whatsapp.net": {
      "vip": false,
      "ban": false,
      "afkTime": -1,
      "afkReason": "",
      "limit": 20,
      "uang": 10000,
      "lastclaim": 1744438718105,
      "lastbegal": 1744438718105,
      "lastrampok": 1744438718105
    },
    "62895325517794@s.whatsapp.net": {
      "vip": false,
      "ban": false,
      "afkTime": -1,
      "afkReason": "",
      "limit": 20,
      "uang": 10000,
      "lastclaim": 1744438781569,
      "lastbegal": 1744438781569,
      "lastrampok": 1744438781569
    },
    "6281363012968@s.whatsapp.net": {
      "vip": false,
      "ban": false,
      "afkTime": -1,
      "afkReason": "",
      "limit": 20,
      "uang": 10000,
      "lastclaim": 1744439978454,
      "lastbegal": 1744439978454,
      "lastrampok": 1744439978454
    },
    "6285648119845@s.whatsapp.net": {
      "vip": false,
      "ban": false,
      "afkTime": -1,
      "afkReason": "",
      "limit": 20,
      "uang": 10000,
      "lastclaim": 1744440926049,
      "lastbegal": 1744440926049,
      "lastrampok": 1744440926049
    },
    "6281278266425@s.whatsapp.net": {
      "vip": false,
      "ban": false,
      "afkTime": -1,
      "afkReason": "",
      "limit": 20,
      "uang": 10000,
      "lastclaim": 1744443491834,
      "lastbegal": 1744443491834,
      "lastrampok": 1744443491834
    },
    "6281273931379@s.whatsapp.net": {
      "vip": false,
      "ban": false,
      "afkTime": -1,
      "afkReason": "",
      "limit": 20,
      "uang": 10000,
      "lastclaim": 1744443645468,
      "lastbegal": 1744443645468,
      "lastrampok": 1744443645468
    },
    "6288269753652@s.whatsapp.net": {
      "vip": false,
      "ban": false,
      "afkTime": -1,
      "afkReason": "",
      "limit": 20,
      "uang": 10000,
      "lastclaim": 1744444649397,
      "lastbegal": 1744444649397,
      "lastrampok": 1744444649397
    },
    "6287867717820@s.whatsapp.net": {
      "vip": false,
      "ban": false,
      "afkTime": -1,
      "afkReason": "",
      "limit": 20,
      "uang": 10000,
      "lastclaim": 1744477906198,
      "lastbegal": 1744477906198,
      "lastrampok": 1744477906198
    },
    "6285771032048@s.whatsapp.net": {
      "vip": false,
      "ban": false,
      "afkTime": -1,
      "afkReason": "",
      "limit": 20,
      "uang": 10000,
      "lastclaim": 1744477918120,
      "lastbegal": 1744477918120,
      "lastrampok": 1744477918120
    }
  },
  "game": {
    "suit": {},
    "chat_ai": {},
    "menfes": {},
    "tekateki": {},
    "akinator": {},
    "tictactoe": {},
    "tebaklirik": {},
    "kuismath": {},
    "tebaklagu": {},
    "tebakkata": {},
    "family100": {},
    "susunkata": {},
    "tebakbom": {},
    "tebakkimia": {},
    "caklontong": {},
    "tebakangka": {},
    "tebaknegara": {},
    "tebakgambar": {},
    "tebakbendera": {}
  },
  "groups": {
    "120363333225047674@g.us": {
      "url": "",
      "text": {
        "setwelcome": "halo kontol",
        "setleave": "cabut lu babi"
      },
      "warn": {
        "6282137829041@s.whatsapp.net": 1
      },
      "tagsw": {},
      "nsfw": false,
      "mute": false,
      "leave": false,
      "setinfo": false,
      "antilink": false,
      "demote": false,
      "antitoxic": false,
      "promote": false,
      "welcome": true,
      "antivirtex": false,
      "antitagsw": false,
      "antidelete": false,
      "antihidetag": false,
      "waktusholat": false
    },
    "120363418093225769@g.us": {
      "url": "",
      "text": {},
      "warn": {},
      "tagsw": {},
      "nsfw": false,
      "mute": false,
      "leave": false,
      "setinfo": false,
      "antilink": false,
      "demote": false,
      "antitoxic": false,
      "promote": false,
      "welcome": false,
      "antivirtex": false,
      "antitagsw": false,
      "antidelete": false,
      "antihidetag": false,
      "waktusholat": false
    },
    "120363040135174965@g.us": {
      "url": "",
      "text": {},
      "warn": {},
      "tagsw": {},
      "nsfw": false,
      "mute": false,
      "leave": false,
      "setinfo": false,
      "antilink": false,
      "demote": false,
      "antitoxic": false,
      "promote": false,
      "welcome": false,
      "antivirtex": false,
      "antitagsw": false,
      "antidelete": false,
      "antihidetag": false,
      "waktusholat": false
    },
    "120363406506433940@g.us": {
      "url": "",
      "text": {},
      "warn": {},
      "tagsw": {},
      "nsfw": false,
      "mute": false,
      "leave": false,
      "setinfo": false,
      "antilink": false,
      "demote": false,
      "antitoxic": false,
      "promote": false,
      "welcome": false,
      "antivirtex": false,
      "antitagsw": false,
      "antidelete": false,
      "antihidetag": false,
      "waktusholat": false
    },
    "120363418833852090@g.us": {
      "url": "",
      "text": {},
      "warn": {},
      "tagsw": {},
      "nsfw": false,
      "mute": false,
      "leave": false,
      "setinfo": false,
      "antilink": false,
      "demote": false,
      "antitoxic": false,
      "promote": false,
      "welcome": false,
      "antivirtex": false,
      "antitagsw": false,
      "antidelete": false,
      "antihidetag": false,
      "waktusholat": false
    }
  },
  "database": {},
  "premium": [
    {
      "id": "6285793466439@s.whatsapp.net",
      "expired": 1747028439889
    }
  ],
  "sewa": []
}